nus/__init__.py
nus/__main__.py
nus/_version.py
nus/config.py
nus/logging_setup.py
nus/main.py
nus/py.typed
nus-0.1.0.dist-info/METADATA
nus-0.1.0.dist-info/WHEEL
nus-0.1.0.dist-info/entry_points.txt
nus-0.1.0.dist-info/licenses/LICENSE
nus-0.1.0.dist-info/RECORD
