Metadata-Version: 2.4
Name: nus
Version: 0.1.0
Summary: Updates made easy and secure :sunglasses:.
Project-URL: changelog, https://github.com/hasansezertasan/nus/blob/main/CHANGELOG.md
Project-URL: documentation, https://github.com/hasansezertasan/nus#readme
Project-URL: homepage, https://github.com/hasansezertasan/nus
Project-URL: issues, https://github.com/hasansezertasan/nus/issues
Project-URL: releasenotes, https://github.com/hasansezertasan/nus/releases
Project-URL: source, https://github.com/hasansezertasan/nus.git
Author-email: Hasan Sezer Taşan <hasansezertasan@gmail.com>
Maintainer-email: hasansezertasan <hasansezertasan@gmail.com>
License-Expression: MIT
License-File: LICENSE
Keywords: cli,command-line,manager,package,software,theupdateframework,tuf,updates
Classifier: Development Status :: 1 - Planning
Classifier: Environment :: Console
Classifier: Intended Audience :: Developers
Classifier: Intended Audience :: Information Technology
Classifier: Intended Audience :: System Administrators
Classifier: License :: OSI Approved :: MIT License
Classifier: Operating System :: OS Independent
Classifier: Programming Language :: Python
Classifier: Programming Language :: Python :: 3
Classifier: Programming Language :: Python :: 3 :: Only
Classifier: Programming Language :: Python :: 3.8
Classifier: Programming Language :: Python :: 3.9
Classifier: Programming Language :: Python :: 3.10
Classifier: Programming Language :: Python :: 3.11
Classifier: Programming Language :: Python :: 3.12
Classifier: Programming Language :: Python :: 3.13
Classifier: Programming Language :: Python :: Implementation :: CPython
Classifier: Programming Language :: Python :: Implementation :: PyPy
Classifier: Topic :: Internet
Classifier: Topic :: Software Development
Classifier: Topic :: Software Development :: Libraries
Classifier: Topic :: Software Development :: Libraries :: Python Modules
Classifier: Topic :: Terminals
Classifier: Typing :: Typed
Requires-Python: >=3.8
Requires-Dist: tuf>=6.0.0
Provides-Extra: cli
Requires-Dist: typer>=0.16.0; extra == 'cli'
